{
  "brand_name": "Market News",
  "hashtags": "#MarketNews #GlobalMarkets",
  "topics": [
    {
      "headline": "米FOMC、政策金利を据え置きも年内利下げ見通しを縮小",
      "summary": "米連邦公開市場委員会（FOMC）は政策金利を5.25-5.50%で据え置いたものの、最新のドットチャートでは年内利下げ回数を従来の3回から1回へ下方修正。パウエル議長はインフレ進展が限定的であるとし、データ次第でタカ派的姿勢を維持する姿勢を示した。",
      "source": "Federal Reserve",
      "published_jst": "2025-09-20T23:30:00+09:00",
      "category": "Monetary Policy",
      "region": "US"
    },
    {
      "headline": "日本のコアCPI、前年比+2.8%と予想を上回り円高圧力",
      "summary": "日本の8月コアCPIは前年同月比+2.8%となり市場予想の+2.6%を上回った。エネルギー補助金の縮小とサービス価格の上昇が寄与し、日銀の政策正常化観測が再燃。円相場は一時147円台まで買い戻され、国債利回りも上昇した。",
      "source": "総務省統計局",
      "published_jst": "2025-09-20T08:30:00+09:00",
      "category": "Inflation",
      "region": "Japan"
    },
    {
      "headline": "欧州PMIが連続低下、製造業の縮小が続く",
      "summary": "ユーロ圏9月製造業PMI速報値は43.4と前月から低下し、市場予想の44.2も下回った。輸出需要の減速と在庫調整が重荷となり、景気後退懸念が再燃。ECB理事は追加引き締めに慎重姿勢を示す一方、エネルギー価格の再上昇がインフレ見通しを不安定にしている。",
      "source": "S&P Global",
      "published_jst": "2025-09-19T17:00:00+09:00",
      "category": "Macro",
      "region": "EU"
    }
  ]
}
